<?xml version='1.0' encoding='utf-8'?>
<Gesture Name="four08" Subject="01" NumPts="146">
	<Point X="203" Y="111" T="0" />
	<Point X="202" Y="111" T="1" />
	<Point X="201" Y="111" T="2" />
	<Point X="200" Y="111" T="3" />
	<Point X="199" Y="111" T="4" />
	<Point X="197" Y="111" T="5" />
	<Point X="196" Y="111" T="6" />
	<Point X="195" Y="111" T="7" />
	<Point X="194" Y="111" T="8" />
	<Point X="193" Y="111" T="9" />
	<Point X="192" Y="111" T="10" />
	<Point X="191" Y="111" T="11" />
	<Point X="189" Y="111" T="12" />
	<Point X="188" Y="111" T="13" />
	<Point X="187" Y="111" T="14" />
	<Point X="186" Y="111" T="15" />
	<Point X="185" Y="111" T="16" />
	<Point X="184" Y="111" T="17" />
	<Point X="183" Y="111" T="18" />
	<Point X="181" Y="111" T="19" />
	<Point X="180" Y="111" T="20" />
	<Point X="179" Y="111" T="21" />
	<Point X="178" Y="111" T="22" />
	<Point X="177" Y="111" T="23" />
	<Point X="176" Y="111" T="24" />
	<Point X="175" Y="111" T="25" />
	<Point X="174" Y="111" T="26" />
	<Point X="172" Y="111" T="27" />
	<Point X="171" Y="111" T="28" />
	<Point X="170" Y="111" T="29" />
	<Point X="169" Y="111" T="30" />
	<Point X="168" Y="111" T="31" />
	<Point X="167" Y="111" T="32" />
	<Point X="166" Y="111" T="33" />
	<Point X="164" Y="111" T="34" />
	<Point X="163" Y="111" T="35" />
	<Point X="162" Y="111" T="36" />
	<Point X="161" Y="111" T="37" />
	<Point X="160" Y="111" T="38" />
	<Point X="159" Y="111" T="39" />
	<Point X="158" Y="111" T="40" />
	<Point X="156" Y="111" T="41" />
	<Point X="155" Y="111" T="42" />
	<Point X="154" Y="112" T="43" />
	<Point X="153" Y="112" T="44" />
	<Point X="152" Y="112" T="45" />
	<Point X="151" Y="112" T="46" />
	<Point X="150" Y="112" T="47" />
	<Point X="149" Y="112" T="48" />
	<Point X="150" Y="112" T="49" />
	<Point X="150" Y="111" T="50" />
	<Point X="151" Y="111" T="51" />
	<Point X="151" Y="110" T="52" />
	<Point X="152" Y="110" T="53" />
	<Point X="153" Y="110" T="54" />
	<Point X="153" Y="109" T="55" />
	<Point X="154" Y="109" T="56" />
	<Point X="155" Y="108" T="57" />
	<Point X="156" Y="108" T="58" />
	<Point X="156" Y="106" T="59" />
	<Point X="158" Y="106" T="60" />
	<Point X="158" Y="105" T="61" />
	<Point X="159" Y="105" T="62" />
	<Point X="159" Y="104" T="63" />
	<Point X="160" Y="103" T="64" />
	<Point X="161" Y="103" T="65" />
	<Point X="161" Y="102" T="66" />
	<Point X="162" Y="102" T="67" />
	<Point X="162" Y="101" T="68" />
	<Point X="163" Y="101" T="69" />
	<Point X="163" Y="100" T="70" />
	<Point X="164" Y="99" T="71" />
	<Point X="166" Y="97" T="72" />
	<Point X="166" Y="96" T="73" />
	<Point X="167" Y="96" T="74" />
	<Point X="167" Y="95" T="75" />
	<Point X="167" Y="94" T="76" />
	<Point X="168" Y="94" T="77" />
	<Point X="168" Y="93" T="78" />
	<Point X="169" Y="93" T="79" />
	<Point X="169" Y="92" T="80" />
	<Point X="169" Y="91" T="81" />
	<Point X="170" Y="89" T="82" />
	<Point X="170" Y="88" T="83" />
	<Point X="171" Y="88" T="84" />
	<Point X="171" Y="87" T="85" />
	<Point X="171" Y="86" T="86" />
	<Point X="172" Y="85" T="87" />
	<Point X="172" Y="84" T="88" />
	<Point X="174" Y="83" T="89" />
	<Point X="174" Y="81" T="90" />
	<Point X="175" Y="81" T="91" />
	<Point X="176" Y="81" T="92" />
	<Point X="177" Y="81" T="93" />
	<Point X="177" Y="83" T="94" />
	<Point X="177" Y="84" T="95" />
	<Point X="177" Y="85" T="96" />
	<Point X="177" Y="86" T="97" />
	<Point X="177" Y="87" T="98" />
	<Point X="177" Y="88" T="99" />
	<Point X="177" Y="89" T="100" />
	<Point X="177" Y="91" T="101" />
	<Point X="178" Y="91" T="102" />
	<Point X="178" Y="92" T="103" />
	<Point X="178" Y="93" T="104" />
	<Point X="178" Y="94" T="105" />
	<Point X="178" Y="95" T="106" />
	<Point X="178" Y="96" T="107" />
	<Point X="178" Y="97" T="108" />
	<Point X="178" Y="99" T="109" />
	<Point X="178" Y="100" T="110" />
	<Point X="178" Y="101" T="111" />
	<Point X="178" Y="102" T="112" />
	<Point X="178" Y="103" T="113" />
	<Point X="178" Y="104" T="114" />
	<Point X="178" Y="105" T="115" />
	<Point X="178" Y="106" T="116" />
	<Point X="178" Y="108" T="117" />
	<Point X="178" Y="109" T="118" />
	<Point X="178" Y="110" T="119" />
	<Point X="178" Y="111" T="120" />
	<Point X="178" Y="112" T="121" />
	<Point X="179" Y="113" T="122" />
	<Point X="179" Y="114" T="123" />
	<Point X="179" Y="116" T="124" />
	<Point X="179" Y="117" T="125" />
	<Point X="179" Y="118" T="126" />
	<Point X="179" Y="119" T="127" />
	<Point X="179" Y="120" T="128" />
	<Point X="179" Y="121" T="129" />
	<Point X="179" Y="122" T="130" />
	<Point X="179" Y="124" T="131" />
	<Point X="180" Y="124" T="132" />
	<Point X="180" Y="125" T="133" />
	<Point X="180" Y="126" T="134" />
	<Point X="180" Y="127" T="135" />
	<Point X="180" Y="128" T="136" />
	<Point X="180" Y="129" T="137" />
	<Point X="180" Y="130" T="138" />
	<Point X="181" Y="130" T="139" />
	<Point X="181" Y="132" T="140" />
	<Point X="181" Y="133" T="141" />
	<Point X="181" Y="134" T="142" />
	<Point X="181" Y="135" T="143" />
	<Point X="181" Y="136" T="144" />
	<Point X="181" Y="137" T="145" />
</Gesture>