<Gesture Name = "nine5">
	<Point X="150" Y="56"/>
	<Point X="148" Y="56"/>
	<Point X="145" Y="56"/>
	<Point X="143" Y="56"/>
	<Point X="141" Y="57"/>
	<Point X="138" Y="58"/>
	<Point X="137" Y="59"/>
	<Point X="136" Y="59"/>
	<Point X="135" Y="59"/>
	<Point X="133" Y="60"/>
	<Point X="132" Y="60"/>
	<Point X="131" Y="61"/>
	<Point X="130" Y="62"/>
	<Point X="129" Y="63"/>
	<Point X="128" Y="64"/>
	<Point X="127" Y="64"/>
	<Point X="127" Y="65"/>
	<Point X="126" Y="66"/>
	<Point X="125" Y="66"/>
	<Point X="125" Y="67"/>
	<Point X="125" Y="68"/>
	<Point X="124" Y="69"/>
	<Point X="124" Y="70"/>
	<Point X="123" Y="71"/>
	<Point X="123" Y="72"/>
	<Point X="123" Y="73"/>
	<Point X="122" Y="73"/>
	<Point X="122" Y="74"/>
	<Point X="122" Y="75"/>
	<Point X="122" Y="76"/>
	<Point X="122" Y="77"/>
	<Point X="122" Y="78"/>
	<Point X="122" Y="79"/>
	<Point X="122" Y="80"/>
	<Point X="122" Y="81"/>
	<Point X="122" Y="82"/>
	<Point X="122" Y="83"/>
	<Point X="123" Y="83"/>
	<Point X="123" Y="84"/>
	<Point X="123" Y="85"/>
	<Point X="124" Y="85"/>
	<Point X="125" Y="85"/>
	<Point X="126" Y="85"/>
	<Point X="128" Y="86"/>
	<Point X="130" Y="86"/>
	<Point X="131" Y="86"/>
	<Point X="132" Y="86"/>
	<Point X="134" Y="86"/>
	<Point X="136" Y="86"/>
	<Point X="138" Y="86"/>
	<Point X="139" Y="85"/>
	<Point X="141" Y="85"/>
	<Point X="142" Y="85"/>
	<Point X="144" Y="84"/>
	<Point X="145" Y="84"/>
	<Point X="145" Y="83"/>
	<Point X="146" Y="83"/>
	<Point X="147" Y="83"/>
	<Point X="148" Y="82"/>
	<Point X="148" Y="81"/>
	<Point X="149" Y="81"/>
	<Point X="149" Y="80"/>
	<Point X="149" Y="78"/>
	<Point X="150" Y="77"/>
	<Point X="150" Y="76"/>
	<Point X="150" Y="75"/>
	<Point X="150" Y="73"/>
	<Point X="150" Y="72"/>
	<Point X="150" Y="71"/>
	<Point X="150" Y="70"/>
	<Point X="150" Y="69"/>
	<Point X="150" Y="68"/>
	<Point X="150" Y="67"/>
	<Point X="149" Y="66"/>
	<Point X="149" Y="65"/>
	<Point X="149" Y="64"/>
	<Point X="148" Y="63"/>
	<Point X="148" Y="62"/>
	<Point X="148" Y="61"/>
	<Point X="148" Y="60"/>
	<Point X="148" Y="59"/>
	<Point X="148" Y="58"/>
	<Point X="148" Y="57"/>
	<Point X="148" Y="56"/>
	<Point X="148" Y="55"/>
	<Point X="148" Y="56"/>
	<Point X="148" Y="57"/>
	<Point X="148" Y="59"/>
	<Point X="148" Y="61"/>
	<Point X="148" Y="65"/>
	<Point X="148" Y="68"/>
	<Point X="147" Y="71"/>
	<Point X="147" Y="74"/>
	<Point X="147" Y="77"/>
	<Point X="147" Y="80"/>
	<Point X="147" Y="82"/>
	<Point X="147" Y="84"/>
	<Point X="147" Y="85"/>
	<Point X="147" Y="88"/>
	<Point X="147" Y="89"/>
	<Point X="147" Y="91"/>
	<Point X="147" Y="92"/>
	<Point X="147" Y="93"/>
	<Point X="147" Y="94"/>
	<Point X="147" Y="95"/>
	<Point X="147" Y="96"/>
	<Point X="147" Y="97"/>
	<Point X="147" Y="98"/>
	<Point X="147" Y="99"/>
	<Point X="147" Y="100"/>
	<Point X="146" Y="100"/>
	<Point X="146" Y="101"/>
	<Point X="146" Y="103"/>
	<Point X="146" Y="104"/>
	<Point X="146" Y="105"/>
	<Point X="146" Y="106"/>
	<Point X="146" Y="107"/>
	<Point X="145" Y="108"/>
	<Point X="145" Y="109"/>
	<Point X="145" Y="110"/>
	<Point X="145" Y="112"/>
	<Point X="145" Y="113"/>
	<Point X="144" Y="114"/>
	<Point X="144" Y="115"/>
	<Point X="144" Y="116"/>
	<Point X="143" Y="118"/>
	<Point X="143" Y="119"/>
	<Point X="143" Y="120"/>
	<Point X="143" Y="121"/>
	<Point X="143" Y="122"/>
	<Point X="143" Y="123"/>
	<Point X="143" Y="124"/>
	<Point X="143" Y="125"/>
	<Point X="143" Y="126"/>
	<Point X="143" Y="127"/>
	<Point X="143" Y="128"/>
	<Point X="143" Y="129"/>
	<Point X="143" Y="130"/>
	<Point X="143" Y="131"/>
	<Point X="143" Y="132"/>
</Gesture>